pylibtermkey_cpp.cpython-38-darwin.so
.libspylibtermkey_cpp/libtermkey.1.dylib
.libspylibtermkey_cpp/libtermkey.dylib
pylibtermkey/__init__.py
pylibtermkey/test_pylibtermkey.py
pylibtermkey-0.3.1.dist-info/LICENSE
pylibtermkey-0.3.1.dist-info/METADATA
pylibtermkey-0.3.1.dist-info/WHEEL
pylibtermkey-0.3.1.dist-info/top_level.txt
pylibtermkey-0.3.1.dist-info/RECORD
