Metadata-Version: 2.1
Name: pylibtermkey
Version: 0.3.1
Summary: Python bindings for libtermkey
Home-page: https://github.com/mvilim/pylibtermkey
Author: Michael Vilim
Author-email: michael.vilim@gmail.com
License: UNKNOWN
Platform: UNKNOWN
Requires-Dist: typing (>3.6) ; python_version < "3.5"
